Reg/reg.vhdl
library ieee;
use ieee.std_logic_1164.all;
use ieee.std_logic_unsigned.all;
use ieee.numeric_std.all;

entity Reg is
	port(
	-- Write Port 1 prioritaire--
		wdata1		: in Std_Logic_Vector(31 downto 0);
		wadr1		: in Std_Logic_Vector(3 downto 0);
		wen1		: in Std_Logic;

	-- Write Port 2 non prioritaire--
		wdata2		: in Std_Logic_Vector(31 downto 0);
		wadr2		: in Std_Logic_Vector(3 downto 0);
		wen2		: in Std_Logic;

	-- Write CSPR Port--
		wcry		: in Std_Logic;
		wzero		: in Std_Logic;
		wneg		: in Std_Logic;
		wovr		: in Std_Logic;
		cspr_wb		: in Std_Logic;
		
	-- Read Port 1 32 bits--
		reg_rd1		: out Std_Logic_Vector(31 downto 0);
		radr1		: in Std_Logic_Vector(3 downto 0);
		reg_v1		: out Std_Logic;

	-- Read Port 2 32 bits--
		reg_rd2		: out Std_Logic_Vector(31 downto 0);
		radr2		: in Std_Logic_Vector(3 downto 0);
		reg_v2		: out Std_Logic;

	-- Read Port 3 32 bits--
		reg_rd3		: out Std_Logic_Vector(31 downto 0);
		radr3		: in Std_Logic_Vector(3 downto 0);
		reg_v3		: out Std_Logic;

	-- read CSPR Port--
		reg_cry		: out Std_Logic;
		reg_zero	: out Std_Logic;
		reg_neg		: out Std_Logic;
		reg_ovr		: out Std_Logic;
		reg_cznv	: out Std_Logic;
		reg_vv		: out Std_Logic;
		
	-- Invalidate Port --
		inval_adr1	: in Std_Logic_Vector(3 downto 0);
		inval1		: in Std_Logic;

		inval_adr2	: in Std_Logic_Vector(3 downto 0);
		inval2		: in Std_Logic;

		inval_czn	: in Std_Logic;
		inval_ovr	: in Std_Logic;

	-- PC--
		reg_pc		: out Std_Logic_Vector(31 downto 0);
		reg_pcv		: out Std_Logic;
		inc_pc		: in Std_Logic;
	
	-- global interface--
		ck			: in Std_Logic;
		reset_n		: in Std_Logic;
		vdd			: in bit;
		vss			: in bit);
end Reg;

architecture Behavior OF Reg is
type registers_array is array (15 downto 0) of std_logic_vector(31 downto 0);
type inval_array     is array (15 downto 0) of std_logic;
signal REGS   : registers_array;
signal invals : inval_array; -- 1 c'est invalid, 0 est valid
signal cry,zero,neg,ovr,cznv,vv : std_logic;
begin 
process(ck)-- write process (sync)
begin
	
	if(rising_edge(ck)) then
		--report "PC ink reg= " & std_logic'image(inc_pc);
		--active low reset
		if(reset_n = '0') then
			for i in invals'range loop
				  invals(i) <= '0';
				  REGS(i)   <= X"00000000";
			end loop;
			report "PC initalized = " & std_logic'image(Regs(15)(0));
			cznv   <= '1';
			vv     <= '1';
		else

			--report "wen1 "& std_logic'image(wen1);
			--report "invalw1" & std_logic'image(invals(to_integer(unsigned(wadr1))));
			--report "invalid1 " & integer'image(to_integer(unsigned(inval_adr1)));

			if( wen1 = '1' and wen2 = '1' and wadr1 = wadr2 
				and invals(to_integer(unsigned(wadr1))) = '1'
				and invals(to_integer(unsigned(wadr2))) = '1') 
			then
				report "writing port 1 ("& to_hstring(wadr1) &")= " & to_hstring(wdata1);
				REGS(to_integer(unsigned(wadr1)))   <= wdata1;
				invals(to_integer(unsigned(wadr1))) <= '0';
			else
				-- write 2 	
				if (wen2 = '1' and invals(to_integer(unsigned(wadr2))) = '1') then
					report "writing port 2 ("& to_hstring(wadr2) &")= " & to_hstring(wdata2);
					REGS(to_integer(unsigned(wadr2)))   <= wdata2;
					invals(to_integer(unsigned(wadr2))) <= '0';
				end if;

				-- write 1
				if(wen1 = '1' and invals(to_integer(unsigned(wadr1))) = '1') then
					report "writing port 1 ("& to_hstring(wadr1) &")= " & to_hstring(wdata1);
					REGS(to_integer(unsigned(wadr1)))   <= wdata1;
					invals(to_integer(unsigned(wadr1))) <= '0';
				end if;

			end if;

			--Flags write back
			if (cspr_wb = '1' and cznv = '0') then
				cry  <= wcry;
				zero <= wzero;
				neg  <= wneg;
				cznv <= '1';
			end if;
			if (cspr_wb = '1' and vv = '0') then
				ovr  <= wovr;
				vv   <= '1';
			end if;

			-- Increment PC
			if inc_pc = '1' and invals(15) = '0' then
				-- report "PC reg_incr = " & std_logic'image(Regs(15)(0));
				REGS(15) <= REGS(15) + 4;
			end if;

			--invalidate Regs and flags (on invalid si c'est valide)
			if 	inval1 = '1' and invals(to_integer(unsigned(inval_adr1))) = '0'then 
				report "invalid1 " & integer'image(to_integer(unsigned(inval_adr1)));	
				invals(to_integer(unsigned(inval_adr1))) <= '1';
			end if;

			if 	inval2 = '1' and invals(to_integer(unsigned(inval_adr2))) = '0' then
				--report "invalid2 " & integer'image(to_integer(unsigned(inval_adr2)));
				invals(to_integer(unsigned(inval_adr2))) <= '1';
			end if;
			
			if inval_czn = '1' and cznv = '1' then
				cznv <= '0';
			end if;

			if inval_ovr = '1' and vv = '1' then
				vv <= '0';
			end if;

		end if;
	end if;
end process;

-- Read (async)
reg_rd1 <= REGS(to_integer(unsigned(radr1)));
reg_rd2 <= REGS(to_integer(unsigned(radr2)));
reg_rd3 <= REGS(to_integer(unsigned(radr3)));

reg_v2  <= not invals(to_integer(unsigned(radr2)));
reg_v1  <= not invals(to_integer(unsigned(radr1)));
reg_v3  <= not invals(to_integer(unsigned(radr3)));

reg_cry  <= cry;
reg_neg  <= neg;
reg_zero <= zero;
reg_ovr  <= ovr;

reg_cznv <= cznv;
reg_vv   <= vv;

reg_pc  <= REGS(15);
reg_pcv <= not invals(15);

end Behavior;

Reg/reg_tb.vhdl
library ieee;
use ieee.std_logic_1164.all;

entity reg_tb is
end entity;

architecture archi of reg_tb is
component reg

	port(
	-- Write Port 1 prioritaire--
		wdata1		: in Std_Logic_Vector(31 downto 0);
		wadr1		: in Std_Logic_Vector(3 downto 0);
		wen1		: in Std_Logic;

	-- Write Port 2 non prioritaire--
		wdata2		: in Std_Logic_Vector(31 downto 0);
		wadr2		: in Std_Logic_Vector(3 downto 0);
		wen2		: in Std_Logic;

	-- Write CSPR Port--
		wcry		: in Std_Logic;
		wzero		: in Std_Logic;
		wneg		: in Std_Logic;
		wovr		: in Std_Logic;
		cspr_wb		: in Std_Logic;
		
	-- Read Port 1 32 bits--
		reg_rd1		: out Std_Logic_Vector(31 downto 0);
		radr1			: in Std_Logic_Vector(3 downto 0);
		reg_v1		: out Std_Logic;

	-- Read Port 2 32 bits--
		reg_rd2		: out Std_Logic_Vector(31 downto 0);
		radr2			: in Std_Logic_Vector(3 downto 0);
		reg_v2		: out Std_Logic;

	-- Read Port 3 32 bits--
		reg_rd3		: out Std_Logic_Vector(31 downto 0);
		radr3			: in Std_Logic_Vector(3 downto 0);
		reg_v3		: out Std_Logic;

	-- read CSPR Port--
		reg_cry		: out Std_Logic;
		reg_zero	: out Std_Logic;
		reg_neg		: out Std_Logic;
		reg_cznv	: out Std_Logic;
		reg_ovr		: out Std_Logic;
		reg_vv		: out Std_Logic;
		
	-- Invalidate Port --
		inval_adr1	: in Std_Logic_Vector(3 downto 0);
		inval1		: in Std_Logic;

		inval_adr2	: in Std_Logic_Vector(3 downto 0);
		inval2		: in Std_Logic;

		inval_czn	: in Std_Logic;
		inval_ovr	: in Std_Logic;

	-- PC--
		reg_pc		: out Std_Logic_Vector(31 downto 0);
		reg_pcv		: out Std_Logic;
		inc_pc		: in Std_Logic;
	
	-- global interface--
		ck			: in Std_Logic;
		reset_n			: in Std_Logic;
		vdd			: in bit;
		vss			: in bit);
end component;

signal wdata1,wdata2,reg_rd1,reg_rd2,reg_rd3,reg_pc : std_logic_vector(31 downto 0);
signal wen1,wen2,wzero,wneg,wcry,wovr,cspr_wb,reg_v1,reg_v2,reg_v3,reg_cry,reg_zero,reg_neg,reg_cznv,reg_ovr,reg_vv,inval1,inval2,inval_czn,inval_ovr,reg_pcv,inc_pc,reset_n : std_logic;
signal ck : std_logic := '1';
signal wadr1,wadr2,radr1, radr2, radr3, inval_adr1, inval_adr2 : std_logic_vector(3 downto 0); 

signal vdd,vss : bit;
signal finished : std_logic;
begin
regs: reg port map (wdata1 => wdata1,
		  wdata2 => wdata2,
		  reg_rd1 => reg_rd1,
		  reg_rd2 => reg_rd2,
		  reg_rd3 => reg_rd3,
		  reg_pc => reg_pc,
		  wen1 => wen1,
		  wen2 => wen2,
		  wzero => wzero,
		  wneg => wneg,
		  wcry => wcry,
		  wovr => wovr,
		  cspr_wb => cspr_wb,
		  reg_v1 => reg_v1,
		  reg_v2 => reg_v2,
		  reg_v3 => reg_v3, 
		  reg_cry => reg_cry,
		  reg_zero => reg_zero,
		  reg_neg => reg_neg,
		  reg_cznv => reg_cznv,
		  reg_ovr => reg_ovr,
		  reg_vv => reg_vv,
		  inval1 => inval1,
		  inval2 => inval2,
		  inval_czn => inval_czn,
		  inval_ovr => inval_ovr,
		  reg_pcv => reg_pcv,
		  inc_pc => inc_pc,
		  ck => ck,
		  reset_n => reset_n,
		  wadr1 => wadr1,
		  wadr2 => wadr2,
		  radr1 => radr1,
		  radr2 => radr2,
		  radr3 => radr3,
		  inval_adr1 => inval_adr1,
		  inval_adr2 => inval_adr2,
		  vdd => vdd,
		  vss => vss);
finished <= '0';


process
begin
	for i in 0 to 20 loop
		ck <= not ck after 5 ms;
		wait for 5 ms;
	end loop; 	
wait;
end process;

process
	begin

	reset_n <= '0';
wait for 10 ms;
	reset_n <= '1';
	wdata1 <= "10000000110000011000000110000001";
	wadr1 <= "1111";
	wen1 <= '1';
	wdata2 <= "11111111111111000001111111111111";
	wadr2 <= "0001";
	wen2 <= '1';
wait for 10 ms;	
	wdata2 <= "00011111111111000001111111111001";
	wadr2 <= "0101";
	wen2 <= '1';
wait for 10 ms;
	wen1 <= '0';
	wen2 <= '0';
	radr1 <= "1111";
	radr2 <= "0000";
wait for 10 ms;
	radr2 <= "0001";
wait for 10 ms;
	radr2 <= "0010";
wait for 10 ms;
	radr2 <= "0011";
wait for 10 ms;
	radr2 <= "0100";
wait for 10 ms;
	radr2 <= "0101";
wait for 10 ms;
	radr2 <= "0110";
wait for 10 ms;
	radr2 <= "0111";
wait for 10 ms;
	radr2 <= "1000";
wait for 10 ms;
	radr2 <= "1001";
wait for 10 ms;
	radr2 <= "1010";
wait for 10 ms;
	radr2 <= "1011";
wait for 10 ms;
	radr2 <= "1100";
wait for 10 ms;
	radr2 <= "1101";
wait for 10 ms;
	radr2 <= "1110";
wait for 10 ms;
	radr2 <= "1111";
wait for 10 ms;
	assert reg_rd1="10000000110000011000000110000001" report "Erreur sur reg val" severity error; 
	assert reg_v1='0' report "Erreur sur validite" severity error;	
	assert false report "end of test" severity note;
wait;
end process;
end archi;

Reg/reg.vcd
$date
  Wed Dec 25 14:36:32 2019
$end
$version
  GHDL v0
$end
$timescale
  1 fs
$end
$scope module standard $end
$upscope $end
$scope module std_logic_1164 $end
$upscope $end
$scope module std_logic_arith $end
$upscope $end
$scope module std_logic_unsigned $end
$upscope $end
$scope module numeric_std $end
$upscope $end
$scope module reg_tb $end
$var reg 32 ! wdata1[31:0] $end
$var reg 32 " wdata2[31:0] $end
$var reg 32 # reg_rd1[31:0] $end
$var reg 32 $ reg_rd2[31:0] $end
$var reg 32 % reg_rd3[31:0] $end
$var reg 32 & reg_pc[31:0] $end
$var reg 1 ' wen1 $end
$var reg 1 ( wen2 $end
$var reg 1 ) wzero $end
$var reg 1 * wneg $end
$var reg 1 + wcry $end
$var reg 1 , wovr $end
$var reg 1 - cspr_wb $end
$var reg 1 . reg_v1 $end
$var reg 1 / reg_v2 $end
$var reg 1 0 reg_v3 $end
$var reg 1 1 reg_cry $end
$var reg 1 2 reg_zero $end
$var reg 1 3 reg_neg $end
$var reg 1 4 reg_cznv $end
$var reg 1 5 reg_ovr $end
$var reg 1 6 reg_vv $end
$var reg 1 7 inval1 $end
$var reg 1 8 inval2 $end
$var reg 1 9 inval_czn $end
$var reg 1 : inval_ovr $end
$var reg 1 ; reg_pcv $end
$var reg 1 < inc_pc $end
$var reg 1 = reset_n $end
$var reg 1 > ck $end
$var reg 4 ? wadr1[3:0] $end
$var reg 4 @ wadr2[3:0] $end
$var reg 4 A radr1[3:0] $end
$var reg 4 B radr2[3:0] $end
$var reg 4 C radr3[3:0] $end
$var reg 4 D inval_adr1[3:0] $end
$var reg 4 E inval_adr2[3:0] $end
$var reg 1 F vdd $end
$var reg 1 G vss $end
$var reg 1 H finished $end
$scope module regs $end
$var reg 32 I wdata1[31:0] $end
$var reg 4 J wadr1[3:0] $end
$var reg 1 K wen1 $end
$var reg 32 L wdata2[31:0] $end
$var reg 4 M wadr2[3:0] $end
$var reg 1 N wen2 $end
$var reg 1 O wcry $end
$var reg 1 P wzero $end
$var reg 1 Q wneg $end
$var reg 1 R wovr $end
$var reg 1 S cspr_wb $end
$var reg 32 T reg_rd1[31:0] $end
$var reg 4 U radr1[3:0] $end
$var reg 1 V reg_v1 $end
$var reg 32 W reg_rd2[31:0] $end
$var reg 4 X radr2[3:0] $end
$var reg 1 Y reg_v2 $end
$var reg 32 Z reg_rd3[31:0] $end
$var reg 4 [ radr3[3:0] $end
$var reg 1 \ reg_v3 $end
$var reg 1 ] reg_cry $end
$var reg 1 ^ reg_zero $end
$var reg 1 _ reg_neg $end
$var reg 1 ` reg_cznv $end
$var reg 1 a reg_ovr $end
$var reg 1 b reg_vv $end
$var reg 4 c inval_adr1[3:0] $end
$var reg 1 d inval1 $end
$var reg 4 e inval_adr2[3:0] $end
$var reg 1 f inval2 $end
$var reg 1 g inval_czn $end
$var reg 1 h inval_ovr $end
$var reg 32 i reg_pc[31:0] $end
$var reg 1 j reg_pcv $end
$var reg 1 k inc_pc $end
$var reg 1 l ck $end
$var reg 1 m reset_n $end
$var reg 1 n vdd $end
$var reg 1 o vss $end
$comment regs is not handled $end
$var reg 16 p invals[15:0] $end
$var reg 1 q cry $end
$var reg 1 r zero $end
$var reg 1 s neg $end
$var reg 1 t ovr $end
$var reg 1 u cznv $end
$var reg 1 v vv $end
$upscope $end
$upscope $end
$enddefinitions $end
#0
bUUUUUUUUUUUUUUUUUUUUUUUUUUUUUUUU !
bUUUUUUUUUUUUUUUUUUUUUUUUUUUUUUUU "
bUUUUUUUUUUUUUUUUUUUUUUUUUUUUUUUU #
bUUUUUUUUUUUUUUUUUUUUUUUUUUUUUUUU $
bUUUUUUUUUUUUUUUUUUUUUUUUUUUUUUUU %
bUUUUUUUUUUUUUUUUUUUUUUUUUUUUUUUU &
U'
U(
U)
U*
U+
U,
U-
U.
U/
U0
U1
U2
U3
U4
U5
U6
U7
U8
U9
U:
U;
U<
0=
1>
bUUUU ?
bUUUU @
bUUUU A
bUUUU B
bUUUU C
bUUUU D
bUUUU E
0F
0G
0H
bUUUUUUUUUUUUUUUUUUUUUUUUUUUUUUUU I
bUUUU J
UK
bUUUUUUUUUUUUUUUUUUUUUUUUUUUUUUUU L
bUUUU M
UN
UO
UP
UQ
UR
US
bUUUUUUUUUUUUUUUUUUUUUUUUUUUUUUUU T
bUUUU U
UV
bUUUUUUUUUUUUUUUUUUUUUUUUUUUUUUUU W
bUUUU X
UY
bUUUUUUUUUUUUUUUUUUUUUUUUUUUUUUUU Z
bUUUU [
U\
U]
U^
U_
U`
Ua
Ub
bUUUU c
Ud
bUUUU e
Uf
Ug
Uh
bUUUUUUUUUUUUUUUUUUUUUUUUUUUUUUUU i
Uj
Uk
1l
0m
0n
0o
bUUUUUUUUUUUUUUUU p
Uq
Ur
Us
Ut
Uu
Uv
#5000000000000
0>
0l
#10000000000000
b10000000110000011000000110000001 !
b11111111111111000001111111111111 "
1'
1(
0;
1=
1>
b1111 ?
b0001 @
b10000000110000011000000110000001 I
b1111 J
1K
b11111111111111000001111111111111 L
b0001 M
1N
0j
1l
1m
b000000000000000U p
#15000000000000
0>
0l
#20000000000000
b00011111111111000001111111111001 "
b10000000110000011000000110000001 &
1>
b0101 @
b00011111111111000001111111111001 L
b0101 M
b10000000110000011000000110000001 i
1l
#25000000000000
0>
0l
#30000000000000
b10000000110000011000000110000001 #
0'
0(
0.
1>
b1111 A
b0000 B
0K
0N
b10000000110000011000000110000001 T
b1111 U
0V
b0000 X
1l
#35000000000000
0>
0l
#40000000000000
b11111111111111000001111111111111 $
0/
1>
b0001 B
b11111111111111000001111111111111 W
b0001 X
0Y
1l
#45000000000000
0>
0l
#50000000000000
bUUUUUUUUUUUUUUUUUUUUUUUUUUUUUUUU $
1>
b0010 B
bUUUUUUUUUUUUUUUUUUUUUUUUUUUUUUUU W
b0010 X
1l
#55000000000000
0>
0l
#60000000000000
1>
b0011 B
b0011 X
1l
#65000000000000
0>
0l
#70000000000000
1>
b0100 B
b0100 X
1l
#75000000000000
0>
0l
#80000000000000
b00011111111111000001111111111001 $
1>
b0101 B
b00011111111111000001111111111001 W
b0101 X
1l
#85000000000000
0>
0l
#90000000000000
bUUUUUUUUUUUUUUUUUUUUUUUUUUUUUUUU $
1>
b0110 B
bUUUUUUUUUUUUUUUUUUUUUUUUUUUUUUUU W
b0110 X
1l
#95000000000000
0>
0l
#100000000000000
1>
b0111 B
b0111 X
1l
#105000000000000
0>
0l
#110000000000000
b1000 B
b1000 X
#120000000000000
b1001 B
b1001 X
#130000000000000
b1010 B
b1010 X
#140000000000000
b1011 B
b1011 X
#150000000000000
b1100 B
b1100 X
#160000000000000
b1101 B
b1101 X
#170000000000000
b1110 B
b1110 X
#180000000000000
b10000000110000011000000110000001 $
b1111 B
b10000000110000011000000110000001 W
b1111 X
